_version.py
api_post.py
api_ptt.py
mcp_server.py
utils.py
ptt_mcp_server-0.1.2.dist-info/licenses/LICENSE
ptt_mcp_server-0.1.2.dist-info/METADATA
ptt_mcp_server-0.1.2.dist-info/WHEEL
ptt_mcp_server-0.1.2.dist-info/entry_points.txt
ptt_mcp_server-0.1.2.dist-info/top_level.txt
ptt_mcp_server-0.1.2.dist-info/RECORD
