Metadata-Version: 2.4
Name: ptt-mcp-server
Version: 0.1.2
Summary: The best MCP server for PTT.
Home-page: https://github.com/PyPtt/ptt_mcp_server
Author: CodingMan
Author-email: pttcodingman@gmail.com
Classifier: Development Status :: 4 - Beta
Classifier: Programming Language :: Python :: 3.10
Classifier: Programming Language :: Python :: 3.11
Classifier: Programming Language :: Python :: 3.12
Classifier: License :: OSI Approved :: BSD License
Classifier: Operating System :: OS Independent
Requires-Python: >=3.10
License-File: LICENSE
Requires-Dist: pyptt
Requires-Dist: fastmcp
Requires-Dist: python-dotenv
Dynamic: author
Dynamic: author-email
Dynamic: classifier
Dynamic: description
Dynamic: description-content-type
Dynamic: home-page
Dynamic: license-file
Dynamic: requires-dist
Dynamic: requires-python
Dynamic: summary
